phone_gen/__init__.py
phone_gen/__version__.py
phone_gen/_phone_number.py
phone_gen/alt_patterns.py
phone_gen/cli.py
phone_gen/country_name.py
phone_gen/iso3.py
phone_gen/patterns.py
phone_gen-3.0.24.dist-info/licenses/LICENSE
phone_gen-3.0.24.dist-info/METADATA
phone_gen-3.0.24.dist-info/WHEEL
phone_gen-3.0.24.dist-info/entry_points.txt
phone_gen-3.0.24.dist-info/top_level.txt
phone_gen-3.0.24.dist-info/RECORD
